<!-- Calculates DSM (all returns) -->
<?xml version="1.0" encoding="utf-8"?>
<Pipeline version="1.0">
  <Writer type="writers.p2g">
    <Option name="grid_dist_x">
      1.0
    </Option>
    <Option name="grid_dist_y">
      1.0
    </Option>
    <Option name="radius">
      0.56419
    </Option>
    <Option name="output_type">
      den 
    </Option>
    <Option name="output_type">
      max 
    </Option>
    <Option name="output_format">
      tif 
    </Option>
      <Reader type="readers.las"></Reader>
  </Writer>
</Pipeline>
